django_visual_editor/__init__.py
django_visual_editor/ai_service.py
django_visual_editor/apps.py
django_visual_editor/fields.py
django_visual_editor/models.py
django_visual_editor/urls.py
django_visual_editor/views.py
django_visual_editor/widgets.py
django_visual_editor/migrations/0001_initial.py
django_visual_editor/migrations/__init__.py
django_visual_editor/static/django_visual_editor/css/admin.css
django_visual_editor/static/django_visual_editor/css/editor.css
django_visual_editor/static/django_visual_editor/js/editor.bundle.js
django_visual_editor/templates/django_visual_editor/widget.html
django_visual_editor-0.5.1.dist-info/licenses/LICENSE
django_visual_editor-0.5.1.dist-info/METADATA
django_visual_editor-0.5.1.dist-info/WHEEL
django_visual_editor-0.5.1.dist-info/top_level.txt
django_visual_editor-0.5.1.dist-info/RECORD
