Metadata-Version: 2.4
Name: django-visual-editor
Version: 0.5.1
Summary: Block-based visual editor for Django with inline styles, image support and rich formatting
Author-email: Vladislav Khoboko <vladislah@gmail.com>
License: MIT
Project-URL: Homepage, https://github.com/hvlads/django-visual-editor
Project-URL: Repository, https://github.com/hvlads/django-visual-editor
Project-URL: Issues, https://github.com/hvlads/django-visual-editor/issues
Keywords: django,editor,wysiwyg,visual-editor,rich-text,html-editor
Classifier: Development Status :: 4 - Beta
Classifier: Environment :: Web Environment
Classifier: Framework :: Django
Classifier: Framework :: Django :: 5.2
Classifier: Intended Audience :: Developers
Classifier: License :: OSI Approved :: MIT License
Classifier: Operating System :: OS Independent
Classifier: Programming Language :: Python
Classifier: Programming Language :: Python :: 3
Classifier: Programming Language :: Python :: 3.9
Classifier: Programming Language :: Python :: 3.10
Classifier: Programming Language :: Python :: 3.11
Classifier: Programming Language :: Python :: 3.12
Classifier: Topic :: Internet :: WWW/HTTP
Classifier: Topic :: Internet :: WWW/HTTP :: Dynamic Content
Classifier: Topic :: Software Development :: Libraries :: Python Modules
Requires-Python: >=3.9
License-File: LICENSE
Requires-Dist: django>=4.2
Requires-Dist: pillow>=10.0.0
Provides-Extra: ai
Requires-Dist: openai>=1.0.0; extra == "ai"
Dynamic: license-file
